{
    "uid": "2f52cf85-b9e3-4bfb-b6d7-9aff562b8ee5",
    "name": "48_ExtraTrees",
    "preprocessing": [
        {
            "ml_task": "binary_classification",
            "params": {
                "columns_preprocessing": {},
                "target_preprocessing": [
                    "na_exclude"
                ],
                "ml_task": "binary_classification"
            }
        },
        {
            "ml_task": "binary_classification",
            "params": {
                "columns_preprocessing": {},
                "target_preprocessing": [
                    "na_exclude"
                ],
                "ml_task": "binary_classification"
            }
        },
        {
            "ml_task": "binary_classification",
            "params": {
                "columns_preprocessing": {},
                "target_preprocessing": [
                    "na_exclude"
                ],
                "ml_task": "binary_classification"
            }
        },
        {
            "ml_task": "binary_classification",
            "params": {
                "columns_preprocessing": {},
                "target_preprocessing": [
                    "na_exclude"
                ],
                "ml_task": "binary_classification"
            }
        },
        {
            "ml_task": "binary_classification",
            "params": {
                "columns_preprocessing": {},
                "target_preprocessing": [
                    "na_exclude"
                ],
                "ml_task": "binary_classification"
            }
        },
        {
            "ml_task": "binary_classification",
            "params": {
                "columns_preprocessing": {},
                "target_preprocessing": [
                    "na_exclude"
                ],
                "ml_task": "binary_classification"
            }
        },
        {
            "ml_task": "binary_classification",
            "params": {
                "columns_preprocessing": {},
                "target_preprocessing": [
                    "na_exclude"
                ],
                "ml_task": "binary_classification"
            }
        },
        {
            "ml_task": "binary_classification",
            "params": {
                "columns_preprocessing": {},
                "target_preprocessing": [
                    "na_exclude"
                ],
                "ml_task": "binary_classification"
            }
        },
        {
            "ml_task": "binary_classification",
            "params": {
                "columns_preprocessing": {},
                "target_preprocessing": [
                    "na_exclude"
                ],
                "ml_task": "binary_classification"
            }
        },
        {
            "ml_task": "binary_classification",
            "params": {
                "columns_preprocessing": {},
                "target_preprocessing": [
                    "na_exclude"
                ],
                "ml_task": "binary_classification"
            }
        }
    ],
    "learners": [
        {
            "library_version": "1.6.1",
            "algorithm_name": "Extra Trees Classifier",
            "algorithm_short_name": "Extra Trees",
            "uid": "8f09208f-bbbb-4ba5-9e43-3d47d308b14f",
            "params": {
                "model_type": "Extra Trees",
                "ml_task": "binary_classification",
                "n_jobs": -1,
                "seed": 1235,
                "criterion": "gini",
                "max_features": 0.5,
                "min_samples_split": 20,
                "max_depth": 4,
                "eval_metric_name": "logloss",
                "explain_level": 0
            },
            "name": "learner_fold_0"
        },
        {
            "library_version": "1.6.1",
            "algorithm_name": "Extra Trees Classifier",
            "algorithm_short_name": "Extra Trees",
            "uid": "e20a476b-1471-4650-967d-af456c215e03",
            "params": {
                "model_type": "Extra Trees",
                "ml_task": "binary_classification",
                "n_jobs": -1,
                "seed": 1235,
                "criterion": "gini",
                "max_features": 0.5,
                "min_samples_split": 20,
                "max_depth": 4,
                "eval_metric_name": "logloss",
                "explain_level": 0
            },
            "name": "learner_fold_1"
        },
        {
            "library_version": "1.6.1",
            "algorithm_name": "Extra Trees Classifier",
            "algorithm_short_name": "Extra Trees",
            "uid": "0e29a1ed-a79c-41cb-937e-c3b115db186a",
            "params": {
                "model_type": "Extra Trees",
                "ml_task": "binary_classification",
                "n_jobs": -1,
                "seed": 1235,
                "criterion": "gini",
                "max_features": 0.5,
                "min_samples_split": 20,
                "max_depth": 4,
                "eval_metric_name": "logloss",
                "explain_level": 0
            },
            "name": "learner_fold_2"
        },
        {
            "library_version": "1.6.1",
            "algorithm_name": "Extra Trees Classifier",
            "algorithm_short_name": "Extra Trees",
            "uid": "3638b7cd-8245-423f-ab4a-efb1951d917a",
            "params": {
                "model_type": "Extra Trees",
                "ml_task": "binary_classification",
                "n_jobs": -1,
                "seed": 1235,
                "criterion": "gini",
                "max_features": 0.5,
                "min_samples_split": 20,
                "max_depth": 4,
                "eval_metric_name": "logloss",
                "explain_level": 0
            },
            "name": "learner_fold_3"
        },
        {
            "library_version": "1.6.1",
            "algorithm_name": "Extra Trees Classifier",
            "algorithm_short_name": "Extra Trees",
            "uid": "8d8d8fe1-c106-42c9-9fba-d9042c0adfe3",
            "params": {
                "model_type": "Extra Trees",
                "ml_task": "binary_classification",
                "n_jobs": -1,
                "seed": 1235,
                "criterion": "gini",
                "max_features": 0.5,
                "min_samples_split": 20,
                "max_depth": 4,
                "eval_metric_name": "logloss",
                "explain_level": 0
            },
            "name": "learner_fold_4"
        },
        {
            "library_version": "1.6.1",
            "algorithm_name": "Extra Trees Classifier",
            "algorithm_short_name": "Extra Trees",
            "uid": "f7d203fb-cd6a-4ebf-b186-7837ace45fd8",
            "params": {
                "model_type": "Extra Trees",
                "ml_task": "binary_classification",
                "n_jobs": -1,
                "seed": 1235,
                "criterion": "gini",
                "max_features": 0.5,
                "min_samples_split": 20,
                "max_depth": 4,
                "eval_metric_name": "logloss",
                "explain_level": 0
            },
            "name": "learner_fold_5"
        },
        {
            "library_version": "1.6.1",
            "algorithm_name": "Extra Trees Classifier",
            "algorithm_short_name": "Extra Trees",
            "uid": "bed52bad-0fed-4cb9-ac82-16c5e6ec98e9",
            "params": {
                "model_type": "Extra Trees",
                "ml_task": "binary_classification",
                "n_jobs": -1,
                "seed": 1235,
                "criterion": "gini",
                "max_features": 0.5,
                "min_samples_split": 20,
                "max_depth": 4,
                "eval_metric_name": "logloss",
                "explain_level": 0
            },
            "name": "learner_fold_6"
        },
        {
            "library_version": "1.6.1",
            "algorithm_name": "Extra Trees Classifier",
            "algorithm_short_name": "Extra Trees",
            "uid": "577b6c06-a620-4e8d-bcf2-15eed4190a1d",
            "params": {
                "model_type": "Extra Trees",
                "ml_task": "binary_classification",
                "n_jobs": -1,
                "seed": 1235,
                "criterion": "gini",
                "max_features": 0.5,
                "min_samples_split": 20,
                "max_depth": 4,
                "eval_metric_name": "logloss",
                "explain_level": 0
            },
            "name": "learner_fold_7"
        },
        {
            "library_version": "1.6.1",
            "algorithm_name": "Extra Trees Classifier",
            "algorithm_short_name": "Extra Trees",
            "uid": "611210e6-c4bd-4217-a540-8ff7ac3d09a9",
            "params": {
                "model_type": "Extra Trees",
                "ml_task": "binary_classification",
                "n_jobs": -1,
                "seed": 1235,
                "criterion": "gini",
                "max_features": 0.5,
                "min_samples_split": 20,
                "max_depth": 4,
                "eval_metric_name": "logloss",
                "explain_level": 0
            },
            "name": "learner_fold_8"
        },
        {
            "library_version": "1.6.1",
            "algorithm_name": "Extra Trees Classifier",
            "algorithm_short_name": "Extra Trees",
            "uid": "aa8998ae-db3e-4487-a676-171ea415ef41",
            "params": {
                "model_type": "Extra Trees",
                "ml_task": "binary_classification",
                "n_jobs": -1,
                "seed": 1235,
                "criterion": "gini",
                "max_features": 0.5,
                "min_samples_split": 20,
                "max_depth": 4,
                "eval_metric_name": "logloss",
                "explain_level": 0
            },
            "name": "learner_fold_9"
        }
    ],
    "params": {
        "additional": {
            "trees_in_step": 100,
            "max_steps": 50,
            "early_stopping_rounds": 50,
            "max_rows_limit": null,
            "max_cols_limit": null
        },
        "preprocessing": {
            "columns_preprocessing": {},
            "target_preprocessing": [
                "na_exclude"
            ],
            "ml_task": "binary_classification"
        },
        "validation_strategy": {
            "validation_type": "kfold",
            "shuffle": true,
            "stratify": true,
            "X_path": "AutoML_results_compete_logloss\\X.data",
            "y_path": "AutoML_results_compete_logloss\\y.data",
            "results_path": "AutoML_results_compete_logloss",
            "k_folds": 10
        },
        "learner": {
            "model_type": "Extra Trees",
            "ml_task": "binary_classification",
            "n_jobs": -1,
            "seed": 1235,
            "criterion": "gini",
            "max_features": 0.5,
            "min_samples_split": 20,
            "max_depth": 4,
            "eval_metric_name": "logloss",
            "explain_level": 0
        },
        "automl_random_state": 1234,
        "ml_task": "binary_classification",
        "explain_level": 0,
        "name": "48_ExtraTrees",
        "status": "initialized",
        "final_loss": null,
        "train_time": null,
        "data_type": "original",
        "max_time_for_learner": 60
    },
    "saved": [
        "48_ExtraTrees\\learner_fold_0.extra_trees",
        "48_ExtraTrees\\learner_fold_1.extra_trees",
        "48_ExtraTrees\\learner_fold_2.extra_trees",
        "48_ExtraTrees\\learner_fold_3.extra_trees",
        "48_ExtraTrees\\learner_fold_4.extra_trees",
        "48_ExtraTrees\\learner_fold_5.extra_trees",
        "48_ExtraTrees\\learner_fold_6.extra_trees",
        "48_ExtraTrees\\learner_fold_7.extra_trees",
        "48_ExtraTrees\\learner_fold_8.extra_trees",
        "48_ExtraTrees\\learner_fold_9.extra_trees"
    ],
    "predictions_fname": "48_ExtraTrees\\predictions_out_of_folds.csv",
    "metric_name": "logloss",
    "final_loss": "0.1847214249559678",
    "train_time": 12.223974704742432,
    "is_stacked": false,
    "joblib_version": "1.5.0",
    "threshold": 0.5058535926039044
}