{
    "uid": "d5a0c4a5-7577-4714-a1f9-933f4d6923d7",
    "name": "34_RandomForest",
    "preprocessing": [
        {
            "ml_task": "binary_classification",
            "params": {
                "columns_preprocessing": {},
                "target_preprocessing": [
                    "na_exclude"
                ],
                "ml_task": "binary_classification"
            }
        },
        {
            "ml_task": "binary_classification",
            "params": {
                "columns_preprocessing": {},
                "target_preprocessing": [
                    "na_exclude"
                ],
                "ml_task": "binary_classification"
            }
        },
        {
            "ml_task": "binary_classification",
            "params": {
                "columns_preprocessing": {},
                "target_preprocessing": [
                    "na_exclude"
                ],
                "ml_task": "binary_classification"
            }
        },
        {
            "ml_task": "binary_classification",
            "params": {
                "columns_preprocessing": {},
                "target_preprocessing": [
                    "na_exclude"
                ],
                "ml_task": "binary_classification"
            }
        },
        {
            "ml_task": "binary_classification",
            "params": {
                "columns_preprocessing": {},
                "target_preprocessing": [
                    "na_exclude"
                ],
                "ml_task": "binary_classification"
            }
        }
    ],
    "learners": [
        {
            "library_version": "1.6.1",
            "algorithm_name": "Random Forest",
            "algorithm_short_name": "Random Forest",
            "uid": "f522d044-3f66-4225-bdbf-817243e6c7e9",
            "params": {
                "model_type": "Random Forest",
                "ml_task": "binary_classification",
                "n_jobs": -1,
                "seed": 1235,
                "criterion": "gini",
                "max_features": 0.5,
                "min_samples_split": 30,
                "max_depth": 4,
                "eval_metric_name": "f1",
                "explain_level": 1
            },
            "name": "learner_fold_0"
        },
        {
            "library_version": "1.6.1",
            "algorithm_name": "Random Forest",
            "algorithm_short_name": "Random Forest",
            "uid": "8a369eba-8e72-40e1-addb-5838192c1c9b",
            "params": {
                "model_type": "Random Forest",
                "ml_task": "binary_classification",
                "n_jobs": -1,
                "seed": 1235,
                "criterion": "gini",
                "max_features": 0.5,
                "min_samples_split": 30,
                "max_depth": 4,
                "eval_metric_name": "f1",
                "explain_level": 1
            },
            "name": "learner_fold_1"
        },
        {
            "library_version": "1.6.1",
            "algorithm_name": "Random Forest",
            "algorithm_short_name": "Random Forest",
            "uid": "e64afe3b-b7e7-4847-9278-8ee423a068a6",
            "params": {
                "model_type": "Random Forest",
                "ml_task": "binary_classification",
                "n_jobs": -1,
                "seed": 1235,
                "criterion": "gini",
                "max_features": 0.5,
                "min_samples_split": 30,
                "max_depth": 4,
                "eval_metric_name": "f1",
                "explain_level": 1
            },
            "name": "learner_fold_2"
        },
        {
            "library_version": "1.6.1",
            "algorithm_name": "Random Forest",
            "algorithm_short_name": "Random Forest",
            "uid": "0d6fcc0f-b142-4f61-ac10-07c15ae19dcb",
            "params": {
                "model_type": "Random Forest",
                "ml_task": "binary_classification",
                "n_jobs": -1,
                "seed": 1235,
                "criterion": "gini",
                "max_features": 0.5,
                "min_samples_split": 30,
                "max_depth": 4,
                "eval_metric_name": "f1",
                "explain_level": 1
            },
            "name": "learner_fold_3"
        },
        {
            "library_version": "1.6.1",
            "algorithm_name": "Random Forest",
            "algorithm_short_name": "Random Forest",
            "uid": "b3ef1c0c-d583-429c-97ac-509c5a500242",
            "params": {
                "model_type": "Random Forest",
                "ml_task": "binary_classification",
                "n_jobs": -1,
                "seed": 1235,
                "criterion": "gini",
                "max_features": 0.5,
                "min_samples_split": 30,
                "max_depth": 4,
                "eval_metric_name": "f1",
                "explain_level": 1
            },
            "name": "learner_fold_4"
        }
    ],
    "params": {
        "additional": {
            "trees_in_step": 100,
            "train_cant_improve_limit": 1,
            "min_steps": 1,
            "max_steps": 50,
            "early_stopping_rounds": 50,
            "max_rows_limit": null,
            "max_cols_limit": null
        },
        "preprocessing": {
            "columns_preprocessing": {},
            "target_preprocessing": [
                "na_exclude"
            ],
            "ml_task": "binary_classification"
        },
        "validation_strategy": {
            "validation_type": "kfold",
            "k_folds": 5,
            "shuffle": true,
            "stratify": true,
            "X_path": "AutoML_results_perform_f1\\X.data",
            "y_path": "AutoML_results_perform_f1\\y.data",
            "results_path": "AutoML_results_perform_f1"
        },
        "learner": {
            "model_type": "Random Forest",
            "ml_task": "binary_classification",
            "n_jobs": -1,
            "seed": 1235,
            "criterion": "gini",
            "max_features": 0.5,
            "min_samples_split": 30,
            "max_depth": 4,
            "eval_metric_name": "f1",
            "explain_level": 1
        },
        "automl_random_state": 1234,
        "ml_task": "binary_classification",
        "explain_level": 1,
        "name": "34_RandomForest",
        "status": "initialized",
        "final_loss": null,
        "train_time": null,
        "data_type": "original",
        "max_time_for_learner": 60
    },
    "saved": [
        "34_RandomForest\\learner_fold_0.random_forest",
        "34_RandomForest\\learner_fold_1.random_forest",
        "34_RandomForest\\learner_fold_2.random_forest",
        "34_RandomForest\\learner_fold_3.random_forest",
        "34_RandomForest\\learner_fold_4.random_forest"
    ],
    "predictions_fname": "34_RandomForest\\predictions_out_of_folds.csv",
    "metric_name": "f1",
    "final_loss": "-0.9421841541755889",
    "train_time": 29.14529776573181,
    "is_stacked": false,
    "joblib_version": "1.5.0",
    "threshold": 0.5755536800607866,
    "single_prediction_time": 0.1294858455657959
}