{
    "uid": "7c286bd1-9f02-44f6-be4f-0d482c6c6c7b",
    "name": "11_LightGBM",
    "preprocessing": [
        {
            "ml_task": "binary_classification",
            "params": {
                "columns_preprocessing": {},
                "target_preprocessing": [
                    "na_exclude"
                ],
                "ml_task": "binary_classification"
            }
        },
        {
            "ml_task": "binary_classification",
            "params": {
                "columns_preprocessing": {},
                "target_preprocessing": [
                    "na_exclude"
                ],
                "ml_task": "binary_classification"
            }
        },
        {
            "ml_task": "binary_classification",
            "params": {
                "columns_preprocessing": {},
                "target_preprocessing": [
                    "na_exclude"
                ],
                "ml_task": "binary_classification"
            }
        },
        {
            "ml_task": "binary_classification",
            "params": {
                "columns_preprocessing": {},
                "target_preprocessing": [
                    "na_exclude"
                ],
                "ml_task": "binary_classification"
            }
        },
        {
            "ml_task": "binary_classification",
            "params": {
                "columns_preprocessing": {},
                "target_preprocessing": [
                    "na_exclude"
                ],
                "ml_task": "binary_classification"
            }
        }
    ],
    "learners": [
        {
            "library_version": "4.6.0",
            "algorithm_name": "LightGBM",
            "algorithm_short_name": "LightGBM",
            "uid": "04a4b0b2-60aa-4e79-8316-e5a9fa342e81",
            "params": {
                "model_type": "LightGBM",
                "ml_task": "binary_classification",
                "n_jobs": -1,
                "seed": 1235,
                "objective": "binary",
                "num_leaves": 15,
                "learning_rate": 0.05,
                "feature_fraction": 0.8,
                "bagging_fraction": 0.5,
                "min_data_in_leaf": 50,
                "metric": "custom",
                "custom_eval_metric_name": "accuracy",
                "explain_level": 1
            },
            "name": "learner_fold_0"
        },
        {
            "library_version": "4.6.0",
            "algorithm_name": "LightGBM",
            "algorithm_short_name": "LightGBM",
            "uid": "f953587e-cd08-4b16-a1b1-08405e9dea50",
            "params": {
                "model_type": "LightGBM",
                "ml_task": "binary_classification",
                "n_jobs": -1,
                "seed": 1235,
                "objective": "binary",
                "num_leaves": 15,
                "learning_rate": 0.05,
                "feature_fraction": 0.8,
                "bagging_fraction": 0.5,
                "min_data_in_leaf": 50,
                "metric": "custom",
                "custom_eval_metric_name": "accuracy",
                "explain_level": 1
            },
            "name": "learner_fold_1"
        },
        {
            "library_version": "4.6.0",
            "algorithm_name": "LightGBM",
            "algorithm_short_name": "LightGBM",
            "uid": "893b0b94-e1c5-417c-bf2c-193a2d4f9665",
            "params": {
                "model_type": "LightGBM",
                "ml_task": "binary_classification",
                "n_jobs": -1,
                "seed": 1235,
                "objective": "binary",
                "num_leaves": 15,
                "learning_rate": 0.05,
                "feature_fraction": 0.8,
                "bagging_fraction": 0.5,
                "min_data_in_leaf": 50,
                "metric": "custom",
                "custom_eval_metric_name": "accuracy",
                "explain_level": 1
            },
            "name": "learner_fold_2"
        },
        {
            "library_version": "4.6.0",
            "algorithm_name": "LightGBM",
            "algorithm_short_name": "LightGBM",
            "uid": "50b5c851-1f5d-441b-a1ce-95c54caadd39",
            "params": {
                "model_type": "LightGBM",
                "ml_task": "binary_classification",
                "n_jobs": -1,
                "seed": 1235,
                "objective": "binary",
                "num_leaves": 15,
                "learning_rate": 0.05,
                "feature_fraction": 0.8,
                "bagging_fraction": 0.5,
                "min_data_in_leaf": 50,
                "metric": "custom",
                "custom_eval_metric_name": "accuracy",
                "explain_level": 1
            },
            "name": "learner_fold_3"
        },
        {
            "library_version": "4.6.0",
            "algorithm_name": "LightGBM",
            "algorithm_short_name": "LightGBM",
            "uid": "ff570502-fe46-433b-bcd0-542ec402ad22",
            "params": {
                "model_type": "LightGBM",
                "ml_task": "binary_classification",
                "n_jobs": -1,
                "seed": 1235,
                "objective": "binary",
                "num_leaves": 15,
                "learning_rate": 0.05,
                "feature_fraction": 0.8,
                "bagging_fraction": 0.5,
                "min_data_in_leaf": 50,
                "metric": "custom",
                "custom_eval_metric_name": "accuracy",
                "explain_level": 1
            },
            "name": "learner_fold_4"
        }
    ],
    "params": {
        "additional": {
            "max_rounds": 10000,
            "early_stopping_rounds": 50,
            "max_rows_limit": null,
            "max_cols_limit": null
        },
        "preprocessing": {
            "columns_preprocessing": {},
            "target_preprocessing": [
                "na_exclude"
            ],
            "ml_task": "binary_classification"
        },
        "validation_strategy": {
            "validation_type": "kfold",
            "k_folds": 5,
            "shuffle": true,
            "stratify": true,
            "X_path": "AutoML_results_perform_accuracy\\X.data",
            "y_path": "AutoML_results_perform_accuracy\\y.data",
            "results_path": "AutoML_results_perform_accuracy"
        },
        "learner": {
            "model_type": "LightGBM",
            "ml_task": "binary_classification",
            "n_jobs": -1,
            "seed": 1235,
            "objective": "binary",
            "num_leaves": 15,
            "learning_rate": 0.05,
            "feature_fraction": 0.8,
            "bagging_fraction": 0.5,
            "min_data_in_leaf": 50,
            "metric": "custom",
            "custom_eval_metric_name": "accuracy",
            "explain_level": 1
        },
        "automl_random_state": 1234,
        "ml_task": "binary_classification",
        "explain_level": 1,
        "name": "11_LightGBM",
        "status": "initialized",
        "final_loss": null,
        "train_time": null,
        "data_type": "original",
        "max_time_for_learner": 60
    },
    "saved": [
        "11_LightGBM\\learner_fold_0.lightgbm",
        "11_LightGBM\\learner_fold_1.lightgbm",
        "11_LightGBM\\learner_fold_2.lightgbm",
        "11_LightGBM\\learner_fold_3.lightgbm",
        "11_LightGBM\\learner_fold_4.lightgbm"
    ],
    "predictions_fname": "11_LightGBM\\predictions_out_of_folds.csv",
    "metric_name": "accuracy",
    "final_loss": "-0.9388646288209607",
    "train_time": 26.60704255104065,
    "is_stacked": false,
    "joblib_version": "1.5.0",
    "threshold": 0.49468449053522395,
    "single_prediction_time": 0.01190328598022461
}