{
    "uid": "a945026d-cb8e-4cc6-b660-d7da8d4e8398",
    "name": "22_LightGBM",
    "preprocessing": [
        {
            "ml_task": "binary_classification",
            "params": {
                "columns_preprocessing": {},
                "target_preprocessing": [
                    "na_exclude"
                ],
                "ml_task": "binary_classification"
            }
        },
        {
            "ml_task": "binary_classification",
            "params": {
                "columns_preprocessing": {},
                "target_preprocessing": [
                    "na_exclude"
                ],
                "ml_task": "binary_classification"
            }
        },
        {
            "ml_task": "binary_classification",
            "params": {
                "columns_preprocessing": {},
                "target_preprocessing": [
                    "na_exclude"
                ],
                "ml_task": "binary_classification"
            }
        },
        {
            "ml_task": "binary_classification",
            "params": {
                "columns_preprocessing": {},
                "target_preprocessing": [
                    "na_exclude"
                ],
                "ml_task": "binary_classification"
            }
        },
        {
            "ml_task": "binary_classification",
            "params": {
                "columns_preprocessing": {},
                "target_preprocessing": [
                    "na_exclude"
                ],
                "ml_task": "binary_classification"
            }
        },
        {
            "ml_task": "binary_classification",
            "params": {
                "columns_preprocessing": {},
                "target_preprocessing": [
                    "na_exclude"
                ],
                "ml_task": "binary_classification"
            }
        },
        {
            "ml_task": "binary_classification",
            "params": {
                "columns_preprocessing": {},
                "target_preprocessing": [
                    "na_exclude"
                ],
                "ml_task": "binary_classification"
            }
        },
        {
            "ml_task": "binary_classification",
            "params": {
                "columns_preprocessing": {},
                "target_preprocessing": [
                    "na_exclude"
                ],
                "ml_task": "binary_classification"
            }
        },
        {
            "ml_task": "binary_classification",
            "params": {
                "columns_preprocessing": {},
                "target_preprocessing": [
                    "na_exclude"
                ],
                "ml_task": "binary_classification"
            }
        },
        {
            "ml_task": "binary_classification",
            "params": {
                "columns_preprocessing": {},
                "target_preprocessing": [
                    "na_exclude"
                ],
                "ml_task": "binary_classification"
            }
        }
    ],
    "learners": [
        {
            "library_version": "4.6.0",
            "algorithm_name": "LightGBM",
            "algorithm_short_name": "LightGBM",
            "uid": "92824818-f02b-4851-b787-e08ec727f392",
            "params": {
                "model_type": "LightGBM",
                "ml_task": "binary_classification",
                "n_jobs": -1,
                "seed": 1236,
                "objective": "binary",
                "num_leaves": 63,
                "learning_rate": 0.2,
                "feature_fraction": 0.5,
                "bagging_fraction": 1.0,
                "min_data_in_leaf": 10,
                "metric": "binary_logloss",
                "custom_eval_metric_name": null,
                "explain_level": 0
            },
            "name": "learner_fold_0"
        },
        {
            "library_version": "4.6.0",
            "algorithm_name": "LightGBM",
            "algorithm_short_name": "LightGBM",
            "uid": "db138ebc-291d-40ec-a923-5cc7d8f87c7d",
            "params": {
                "model_type": "LightGBM",
                "ml_task": "binary_classification",
                "n_jobs": -1,
                "seed": 1236,
                "objective": "binary",
                "num_leaves": 63,
                "learning_rate": 0.2,
                "feature_fraction": 0.5,
                "bagging_fraction": 1.0,
                "min_data_in_leaf": 10,
                "metric": "binary_logloss",
                "custom_eval_metric_name": null,
                "explain_level": 0
            },
            "name": "learner_fold_1"
        },
        {
            "library_version": "4.6.0",
            "algorithm_name": "LightGBM",
            "algorithm_short_name": "LightGBM",
            "uid": "da880064-d30e-4bf9-8d85-28835528767c",
            "params": {
                "model_type": "LightGBM",
                "ml_task": "binary_classification",
                "n_jobs": -1,
                "seed": 1236,
                "objective": "binary",
                "num_leaves": 63,
                "learning_rate": 0.2,
                "feature_fraction": 0.5,
                "bagging_fraction": 1.0,
                "min_data_in_leaf": 10,
                "metric": "binary_logloss",
                "custom_eval_metric_name": null,
                "explain_level": 0
            },
            "name": "learner_fold_2"
        },
        {
            "library_version": "4.6.0",
            "algorithm_name": "LightGBM",
            "algorithm_short_name": "LightGBM",
            "uid": "307d4fbc-fc7c-46ee-a06b-a1b7d2e59a5a",
            "params": {
                "model_type": "LightGBM",
                "ml_task": "binary_classification",
                "n_jobs": -1,
                "seed": 1236,
                "objective": "binary",
                "num_leaves": 63,
                "learning_rate": 0.2,
                "feature_fraction": 0.5,
                "bagging_fraction": 1.0,
                "min_data_in_leaf": 10,
                "metric": "binary_logloss",
                "custom_eval_metric_name": null,
                "explain_level": 0
            },
            "name": "learner_fold_3"
        },
        {
            "library_version": "4.6.0",
            "algorithm_name": "LightGBM",
            "algorithm_short_name": "LightGBM",
            "uid": "a2a6d1bb-3e76-44e1-b87b-6b3dee4fc32f",
            "params": {
                "model_type": "LightGBM",
                "ml_task": "binary_classification",
                "n_jobs": -1,
                "seed": 1236,
                "objective": "binary",
                "num_leaves": 63,
                "learning_rate": 0.2,
                "feature_fraction": 0.5,
                "bagging_fraction": 1.0,
                "min_data_in_leaf": 10,
                "metric": "binary_logloss",
                "custom_eval_metric_name": null,
                "explain_level": 0
            },
            "name": "learner_fold_4"
        },
        {
            "library_version": "4.6.0",
            "algorithm_name": "LightGBM",
            "algorithm_short_name": "LightGBM",
            "uid": "64ef1b5a-73a4-4ba7-9c79-afa996df1e8d",
            "params": {
                "model_type": "LightGBM",
                "ml_task": "binary_classification",
                "n_jobs": -1,
                "seed": 1236,
                "objective": "binary",
                "num_leaves": 63,
                "learning_rate": 0.2,
                "feature_fraction": 0.5,
                "bagging_fraction": 1.0,
                "min_data_in_leaf": 10,
                "metric": "binary_logloss",
                "custom_eval_metric_name": null,
                "explain_level": 0
            },
            "name": "learner_fold_5"
        },
        {
            "library_version": "4.6.0",
            "algorithm_name": "LightGBM",
            "algorithm_short_name": "LightGBM",
            "uid": "5191f071-f77d-4759-99f1-fae0c27a65ba",
            "params": {
                "model_type": "LightGBM",
                "ml_task": "binary_classification",
                "n_jobs": -1,
                "seed": 1236,
                "objective": "binary",
                "num_leaves": 63,
                "learning_rate": 0.2,
                "feature_fraction": 0.5,
                "bagging_fraction": 1.0,
                "min_data_in_leaf": 10,
                "metric": "binary_logloss",
                "custom_eval_metric_name": null,
                "explain_level": 0
            },
            "name": "learner_fold_6"
        },
        {
            "library_version": "4.6.0",
            "algorithm_name": "LightGBM",
            "algorithm_short_name": "LightGBM",
            "uid": "ff596860-4072-45ed-b119-61320ede3510",
            "params": {
                "model_type": "LightGBM",
                "ml_task": "binary_classification",
                "n_jobs": -1,
                "seed": 1236,
                "objective": "binary",
                "num_leaves": 63,
                "learning_rate": 0.2,
                "feature_fraction": 0.5,
                "bagging_fraction": 1.0,
                "min_data_in_leaf": 10,
                "metric": "binary_logloss",
                "custom_eval_metric_name": null,
                "explain_level": 0
            },
            "name": "learner_fold_7"
        },
        {
            "library_version": "4.6.0",
            "algorithm_name": "LightGBM",
            "algorithm_short_name": "LightGBM",
            "uid": "fb642104-3d10-429b-9107-e0fa0474e35d",
            "params": {
                "model_type": "LightGBM",
                "ml_task": "binary_classification",
                "n_jobs": -1,
                "seed": 1236,
                "objective": "binary",
                "num_leaves": 63,
                "learning_rate": 0.2,
                "feature_fraction": 0.5,
                "bagging_fraction": 1.0,
                "min_data_in_leaf": 10,
                "metric": "binary_logloss",
                "custom_eval_metric_name": null,
                "explain_level": 0
            },
            "name": "learner_fold_8"
        },
        {
            "library_version": "4.6.0",
            "algorithm_name": "LightGBM",
            "algorithm_short_name": "LightGBM",
            "uid": "3914a3e7-0bf0-4bb6-baa9-455409ae76a0",
            "params": {
                "model_type": "LightGBM",
                "ml_task": "binary_classification",
                "n_jobs": -1,
                "seed": 1236,
                "objective": "binary",
                "num_leaves": 63,
                "learning_rate": 0.2,
                "feature_fraction": 0.5,
                "bagging_fraction": 1.0,
                "min_data_in_leaf": 10,
                "metric": "binary_logloss",
                "custom_eval_metric_name": null,
                "explain_level": 0
            },
            "name": "learner_fold_9"
        }
    ],
    "params": {
        "additional": {
            "max_rounds": 10000,
            "early_stopping_rounds": 50,
            "max_rows_limit": null,
            "max_cols_limit": null
        },
        "preprocessing": {
            "columns_preprocessing": {},
            "target_preprocessing": [
                "na_exclude"
            ],
            "ml_task": "binary_classification"
        },
        "validation_strategy": {
            "validation_type": "kfold",
            "shuffle": true,
            "stratify": true,
            "X_path": "AutoML_results_compete_logloss\\X.data",
            "y_path": "AutoML_results_compete_logloss\\y.data",
            "results_path": "AutoML_results_compete_logloss",
            "k_folds": 10
        },
        "learner": {
            "model_type": "LightGBM",
            "ml_task": "binary_classification",
            "n_jobs": -1,
            "seed": 1236,
            "objective": "binary",
            "num_leaves": 63,
            "learning_rate": 0.2,
            "feature_fraction": 0.5,
            "bagging_fraction": 1.0,
            "min_data_in_leaf": 10,
            "metric": "binary_logloss",
            "custom_eval_metric_name": null,
            "explain_level": 0
        },
        "automl_random_state": 1234,
        "ml_task": "binary_classification",
        "explain_level": 0,
        "name": "22_LightGBM",
        "status": "initialized",
        "final_loss": null,
        "train_time": null,
        "data_type": "original",
        "max_time_for_learner": 60
    },
    "saved": [
        "22_LightGBM\\learner_fold_0.lightgbm",
        "22_LightGBM\\learner_fold_1.lightgbm",
        "22_LightGBM\\learner_fold_2.lightgbm",
        "22_LightGBM\\learner_fold_3.lightgbm",
        "22_LightGBM\\learner_fold_4.lightgbm",
        "22_LightGBM\\learner_fold_5.lightgbm",
        "22_LightGBM\\learner_fold_6.lightgbm",
        "22_LightGBM\\learner_fold_7.lightgbm",
        "22_LightGBM\\learner_fold_8.lightgbm",
        "22_LightGBM\\learner_fold_9.lightgbm"
    ],
    "predictions_fname": "22_LightGBM\\predictions_out_of_folds.csv",
    "metric_name": "logloss",
    "final_loss": "0.11972835086413842",
    "train_time": 11.597677230834961,
    "is_stacked": false,
    "joblib_version": "1.5.0",
    "threshold": 0.5749906497032056
}