{
    "uid": "42ede364-af18-49ef-892c-d0c4d4830c5a",
    "name": "31_CatBoost",
    "preprocessing": [
        {
            "ml_task": "binary_classification",
            "params": {
                "columns_preprocessing": {},
                "target_preprocessing": [
                    "na_exclude"
                ],
                "ml_task": "binary_classification"
            }
        },
        {
            "ml_task": "binary_classification",
            "params": {
                "columns_preprocessing": {},
                "target_preprocessing": [
                    "na_exclude"
                ],
                "ml_task": "binary_classification"
            }
        },
        {
            "ml_task": "binary_classification",
            "params": {
                "columns_preprocessing": {},
                "target_preprocessing": [
                    "na_exclude"
                ],
                "ml_task": "binary_classification"
            }
        },
        {
            "ml_task": "binary_classification",
            "params": {
                "columns_preprocessing": {},
                "target_preprocessing": [
                    "na_exclude"
                ],
                "ml_task": "binary_classification"
            }
        },
        {
            "ml_task": "binary_classification",
            "params": {
                "columns_preprocessing": {},
                "target_preprocessing": [
                    "na_exclude"
                ],
                "ml_task": "binary_classification"
            }
        },
        {
            "ml_task": "binary_classification",
            "params": {
                "columns_preprocessing": {},
                "target_preprocessing": [
                    "na_exclude"
                ],
                "ml_task": "binary_classification"
            }
        },
        {
            "ml_task": "binary_classification",
            "params": {
                "columns_preprocessing": {},
                "target_preprocessing": [
                    "na_exclude"
                ],
                "ml_task": "binary_classification"
            }
        },
        {
            "ml_task": "binary_classification",
            "params": {
                "columns_preprocessing": {},
                "target_preprocessing": [
                    "na_exclude"
                ],
                "ml_task": "binary_classification"
            }
        },
        {
            "ml_task": "binary_classification",
            "params": {
                "columns_preprocessing": {},
                "target_preprocessing": [
                    "na_exclude"
                ],
                "ml_task": "binary_classification"
            }
        },
        {
            "ml_task": "binary_classification",
            "params": {
                "columns_preprocessing": {},
                "target_preprocessing": [
                    "na_exclude"
                ],
                "ml_task": "binary_classification"
            }
        }
    ],
    "learners": [
        {
            "library_version": "1.2.8",
            "algorithm_name": "CatBoost",
            "algorithm_short_name": "CatBoost",
            "uid": "06df8636-dd35-4c61-8d54-04ea9f870492",
            "params": {
                "model_type": "CatBoost",
                "ml_task": "binary_classification",
                "n_jobs": -1,
                "seed": 1236,
                "learning_rate": 0.1,
                "depth": 8,
                "rsm": 1.0,
                "loss_function": "Logloss",
                "eval_metric": "Logloss",
                "explain_level": 0
            },
            "name": "learner_fold_0",
            "best_ntree_limit": 894
        },
        {
            "library_version": "1.2.8",
            "algorithm_name": "CatBoost",
            "algorithm_short_name": "CatBoost",
            "uid": "a02720b2-ff6e-4109-a0ae-7a972e2eaa0b",
            "params": {
                "model_type": "CatBoost",
                "ml_task": "binary_classification",
                "n_jobs": -1,
                "seed": 1236,
                "learning_rate": 0.1,
                "depth": 8,
                "rsm": 1.0,
                "loss_function": "Logloss",
                "eval_metric": "Logloss",
                "explain_level": 0
            },
            "name": "learner_fold_1",
            "best_ntree_limit": 51
        },
        {
            "library_version": "1.2.8",
            "algorithm_name": "CatBoost",
            "algorithm_short_name": "CatBoost",
            "uid": "6b6822d0-1ec5-407c-8368-3ab0a218adaa",
            "params": {
                "model_type": "CatBoost",
                "ml_task": "binary_classification",
                "n_jobs": -1,
                "seed": 1236,
                "learning_rate": 0.1,
                "depth": 8,
                "rsm": 1.0,
                "loss_function": "Logloss",
                "eval_metric": "Logloss",
                "explain_level": 0
            },
            "name": "learner_fold_2",
            "best_ntree_limit": 66
        },
        {
            "library_version": "1.2.8",
            "algorithm_name": "CatBoost",
            "algorithm_short_name": "CatBoost",
            "uid": "e55f8eed-9ea8-4dd8-9dd7-d95e56c31f1d",
            "params": {
                "model_type": "CatBoost",
                "ml_task": "binary_classification",
                "n_jobs": -1,
                "seed": 1236,
                "learning_rate": 0.1,
                "depth": 8,
                "rsm": 1.0,
                "loss_function": "Logloss",
                "eval_metric": "Logloss",
                "explain_level": 0
            },
            "name": "learner_fold_3",
            "best_ntree_limit": 52
        },
        {
            "library_version": "1.2.8",
            "algorithm_name": "CatBoost",
            "algorithm_short_name": "CatBoost",
            "uid": "45b42384-ee48-44fa-8625-a92f77b01f2f",
            "params": {
                "model_type": "CatBoost",
                "ml_task": "binary_classification",
                "n_jobs": -1,
                "seed": 1236,
                "learning_rate": 0.1,
                "depth": 8,
                "rsm": 1.0,
                "loss_function": "Logloss",
                "eval_metric": "Logloss",
                "explain_level": 0
            },
            "name": "learner_fold_4",
            "best_ntree_limit": 73
        },
        {
            "library_version": "1.2.8",
            "algorithm_name": "CatBoost",
            "algorithm_short_name": "CatBoost",
            "uid": "0665c55d-c104-45fd-b59d-dc10011f2240",
            "params": {
                "model_type": "CatBoost",
                "ml_task": "binary_classification",
                "n_jobs": -1,
                "seed": 1236,
                "learning_rate": 0.1,
                "depth": 8,
                "rsm": 1.0,
                "loss_function": "Logloss",
                "eval_metric": "Logloss",
                "explain_level": 0
            },
            "name": "learner_fold_5",
            "best_ntree_limit": 1147
        },
        {
            "library_version": "1.2.8",
            "algorithm_name": "CatBoost",
            "algorithm_short_name": "CatBoost",
            "uid": "2c31f717-010a-40db-853f-4e4ed4318587",
            "params": {
                "model_type": "CatBoost",
                "ml_task": "binary_classification",
                "n_jobs": -1,
                "seed": 1236,
                "learning_rate": 0.1,
                "depth": 8,
                "rsm": 1.0,
                "loss_function": "Logloss",
                "eval_metric": "Logloss",
                "explain_level": 0
            },
            "name": "learner_fold_6",
            "best_ntree_limit": 73
        },
        {
            "library_version": "1.2.8",
            "algorithm_name": "CatBoost",
            "algorithm_short_name": "CatBoost",
            "uid": "7014c8c7-7300-47ef-9f09-73fb2192bbdd",
            "params": {
                "model_type": "CatBoost",
                "ml_task": "binary_classification",
                "n_jobs": -1,
                "seed": 1236,
                "learning_rate": 0.1,
                "depth": 8,
                "rsm": 1.0,
                "loss_function": "Logloss",
                "eval_metric": "Logloss",
                "explain_level": 0
            },
            "name": "learner_fold_7",
            "best_ntree_limit": 67
        },
        {
            "library_version": "1.2.8",
            "algorithm_name": "CatBoost",
            "algorithm_short_name": "CatBoost",
            "uid": "5eda85a3-8462-4776-b540-c7f630cbec12",
            "params": {
                "model_type": "CatBoost",
                "ml_task": "binary_classification",
                "n_jobs": -1,
                "seed": 1236,
                "learning_rate": 0.1,
                "depth": 8,
                "rsm": 1.0,
                "loss_function": "Logloss",
                "eval_metric": "Logloss",
                "explain_level": 0
            },
            "name": "learner_fold_8",
            "best_ntree_limit": 801
        },
        {
            "library_version": "1.2.8",
            "algorithm_name": "CatBoost",
            "algorithm_short_name": "CatBoost",
            "uid": "051709c1-47de-498a-b038-0dbdcdccaf60",
            "params": {
                "model_type": "CatBoost",
                "ml_task": "binary_classification",
                "n_jobs": -1,
                "seed": 1236,
                "learning_rate": 0.1,
                "depth": 8,
                "rsm": 1.0,
                "loss_function": "Logloss",
                "eval_metric": "Logloss",
                "explain_level": 0
            },
            "name": "learner_fold_9",
            "best_ntree_limit": 98
        }
    ],
    "params": {
        "additional": {
            "max_rounds": 10000,
            "early_stopping_rounds": 50,
            "max_rows_limit": null,
            "max_cols_limit": null
        },
        "preprocessing": {
            "columns_preprocessing": {},
            "target_preprocessing": [
                "na_exclude"
            ],
            "ml_task": "binary_classification"
        },
        "validation_strategy": {
            "validation_type": "kfold",
            "shuffle": true,
            "stratify": true,
            "X_path": "AutoML_results_compete_logloss\\X.data",
            "y_path": "AutoML_results_compete_logloss\\y.data",
            "results_path": "AutoML_results_compete_logloss",
            "k_folds": 10
        },
        "learner": {
            "model_type": "CatBoost",
            "ml_task": "binary_classification",
            "n_jobs": -1,
            "seed": 1236,
            "learning_rate": 0.1,
            "depth": 8,
            "rsm": 1.0,
            "loss_function": "Logloss",
            "eval_metric": "Logloss",
            "explain_level": 0
        },
        "automl_random_state": 1234,
        "ml_task": "binary_classification",
        "explain_level": 0,
        "name": "31_CatBoost",
        "status": "initialized",
        "final_loss": null,
        "train_time": null,
        "data_type": "original",
        "max_time_for_learner": 60
    },
    "saved": [
        "31_CatBoost\\learner_fold_0.catboost",
        "31_CatBoost\\learner_fold_1.catboost",
        "31_CatBoost\\learner_fold_2.catboost",
        "31_CatBoost\\learner_fold_3.catboost",
        "31_CatBoost\\learner_fold_4.catboost",
        "31_CatBoost\\learner_fold_5.catboost",
        "31_CatBoost\\learner_fold_6.catboost",
        "31_CatBoost\\learner_fold_7.catboost",
        "31_CatBoost\\learner_fold_8.catboost",
        "31_CatBoost\\learner_fold_9.catboost"
    ],
    "predictions_fname": "31_CatBoost\\predictions_out_of_folds.csv",
    "metric_name": "logloss",
    "final_loss": "0.11674458515460642",
    "train_time": 21.904118537902832,
    "is_stacked": false,
    "joblib_version": "1.5.0",
    "threshold": 0.2064979956972718
}