{
    "uid": "a4970a5d-a4c3-4197-b67f-edf0955623ba",
    "name": "44_CatBoost_SelectedFeatures",
    "preprocessing": [
        {
            "ml_task": "binary_classification",
            "drop_features": [
                "COUGHING",
                "GENDER"
            ],
            "params": {
                "columns_preprocessing": {},
                "target_preprocessing": [
                    "na_exclude"
                ],
                "ml_task": "binary_classification",
                "drop_features": [
                    "random_feature",
                    "COUGHING",
                    "GENDER"
                ]
            }
        },
        {
            "ml_task": "binary_classification",
            "drop_features": [
                "COUGHING",
                "GENDER"
            ],
            "params": {
                "columns_preprocessing": {},
                "target_preprocessing": [
                    "na_exclude"
                ],
                "ml_task": "binary_classification",
                "drop_features": [
                    "random_feature",
                    "COUGHING",
                    "GENDER"
                ]
            }
        },
        {
            "ml_task": "binary_classification",
            "drop_features": [
                "COUGHING",
                "GENDER"
            ],
            "params": {
                "columns_preprocessing": {},
                "target_preprocessing": [
                    "na_exclude"
                ],
                "ml_task": "binary_classification",
                "drop_features": [
                    "random_feature",
                    "COUGHING",
                    "GENDER"
                ]
            }
        },
        {
            "ml_task": "binary_classification",
            "drop_features": [
                "COUGHING",
                "GENDER"
            ],
            "params": {
                "columns_preprocessing": {},
                "target_preprocessing": [
                    "na_exclude"
                ],
                "ml_task": "binary_classification",
                "drop_features": [
                    "random_feature",
                    "COUGHING",
                    "GENDER"
                ]
            }
        },
        {
            "ml_task": "binary_classification",
            "drop_features": [
                "COUGHING",
                "GENDER"
            ],
            "params": {
                "columns_preprocessing": {},
                "target_preprocessing": [
                    "na_exclude"
                ],
                "ml_task": "binary_classification",
                "drop_features": [
                    "random_feature",
                    "COUGHING",
                    "GENDER"
                ]
            }
        }
    ],
    "learners": [
        {
            "library_version": "1.2.8",
            "algorithm_name": "CatBoost",
            "algorithm_short_name": "CatBoost",
            "uid": "93a2ad51-6275-4cfb-864c-bb9671af3e4b",
            "params": {
                "model_type": "CatBoost",
                "ml_task": "binary_classification",
                "n_jobs": -1,
                "seed": 1237,
                "learning_rate": 0.2,
                "depth": 6,
                "rsm": 1.0,
                "loss_function": "Logloss",
                "eval_metric": "Logloss",
                "explain_level": 1
            },
            "name": "learner_fold_0",
            "best_ntree_limit": 58
        },
        {
            "library_version": "1.2.8",
            "algorithm_name": "CatBoost",
            "algorithm_short_name": "CatBoost",
            "uid": "1a139d05-fb62-4d08-8487-4635a4acf44e",
            "params": {
                "model_type": "CatBoost",
                "ml_task": "binary_classification",
                "n_jobs": -1,
                "seed": 1237,
                "learning_rate": 0.2,
                "depth": 6,
                "rsm": 1.0,
                "loss_function": "Logloss",
                "eval_metric": "Logloss",
                "explain_level": 1
            },
            "name": "learner_fold_1",
            "best_ntree_limit": 38
        },
        {
            "library_version": "1.2.8",
            "algorithm_name": "CatBoost",
            "algorithm_short_name": "CatBoost",
            "uid": "f5dc3175-8e86-430b-9370-61d0446c540e",
            "params": {
                "model_type": "CatBoost",
                "ml_task": "binary_classification",
                "n_jobs": -1,
                "seed": 1237,
                "learning_rate": 0.2,
                "depth": 6,
                "rsm": 1.0,
                "loss_function": "Logloss",
                "eval_metric": "Logloss",
                "explain_level": 1
            },
            "name": "learner_fold_2",
            "best_ntree_limit": 94
        },
        {
            "library_version": "1.2.8",
            "algorithm_name": "CatBoost",
            "algorithm_short_name": "CatBoost",
            "uid": "723eea9e-6300-45e2-be96-79b3f683c01e",
            "params": {
                "model_type": "CatBoost",
                "ml_task": "binary_classification",
                "n_jobs": -1,
                "seed": 1237,
                "learning_rate": 0.2,
                "depth": 6,
                "rsm": 1.0,
                "loss_function": "Logloss",
                "eval_metric": "Logloss",
                "explain_level": 1
            },
            "name": "learner_fold_3",
            "best_ntree_limit": 44
        },
        {
            "library_version": "1.2.8",
            "algorithm_name": "CatBoost",
            "algorithm_short_name": "CatBoost",
            "uid": "fca22eb9-9872-42b9-a97d-a307f9975fe5",
            "params": {
                "model_type": "CatBoost",
                "ml_task": "binary_classification",
                "n_jobs": -1,
                "seed": 1237,
                "learning_rate": 0.2,
                "depth": 6,
                "rsm": 1.0,
                "loss_function": "Logloss",
                "eval_metric": "Logloss",
                "explain_level": 1
            },
            "name": "learner_fold_4",
            "best_ntree_limit": 56
        }
    ],
    "params": {
        "additional": {
            "max_rounds": 10000,
            "early_stopping_rounds": 50,
            "max_rows_limit": null,
            "max_cols_limit": null
        },
        "preprocessing": {
            "columns_preprocessing": {},
            "target_preprocessing": [
                "na_exclude"
            ],
            "ml_task": "binary_classification",
            "drop_features": [
                "random_feature",
                "COUGHING",
                "GENDER"
            ]
        },
        "validation_strategy": {
            "validation_type": "kfold",
            "k_folds": 5,
            "shuffle": true,
            "stratify": true,
            "X_path": "AutoML_results_perform_logloss\\X.data",
            "y_path": "AutoML_results_perform_logloss\\y.data",
            "results_path": "AutoML_results_perform_logloss"
        },
        "learner": {
            "model_type": "CatBoost",
            "ml_task": "binary_classification",
            "n_jobs": -1,
            "seed": 1237,
            "learning_rate": 0.2,
            "depth": 6,
            "rsm": 1.0,
            "loss_function": "Logloss",
            "eval_metric": "Logloss",
            "explain_level": 1
        },
        "automl_random_state": 1234,
        "ml_task": "binary_classification",
        "explain_level": 1,
        "name": "44_CatBoost_SelectedFeatures",
        "status": "initialized",
        "final_loss": null,
        "train_time": null,
        "data_type": "original_features_selection",
        "max_time_for_learner": 60
    },
    "saved": [
        "44_CatBoost_SelectedFeatures\\learner_fold_0.catboost",
        "44_CatBoost_SelectedFeatures\\learner_fold_1.catboost",
        "44_CatBoost_SelectedFeatures\\learner_fold_2.catboost",
        "44_CatBoost_SelectedFeatures\\learner_fold_3.catboost",
        "44_CatBoost_SelectedFeatures\\learner_fold_4.catboost"
    ],
    "predictions_fname": "44_CatBoost_SelectedFeatures\\predictions_out_of_folds.csv",
    "metric_name": "logloss",
    "final_loss": "0.11175392741346299",
    "train_time": 9.54817247390747,
    "is_stacked": false,
    "joblib_version": "1.5.0",
    "threshold": 0.13701865656437928,
    "single_prediction_time": 0.015933752059936523
}