{
    "uid": "d96c568e-0e9e-4e7b-9b1f-d1754aa95a4d",
    "name": "53_RandomForest",
    "preprocessing": [
        {
            "ml_task": "binary_classification",
            "params": {
                "columns_preprocessing": {},
                "target_preprocessing": [
                    "na_exclude"
                ],
                "ml_task": "binary_classification"
            }
        },
        {
            "ml_task": "binary_classification",
            "params": {
                "columns_preprocessing": {},
                "target_preprocessing": [
                    "na_exclude"
                ],
                "ml_task": "binary_classification"
            }
        },
        {
            "ml_task": "binary_classification",
            "params": {
                "columns_preprocessing": {},
                "target_preprocessing": [
                    "na_exclude"
                ],
                "ml_task": "binary_classification"
            }
        },
        {
            "ml_task": "binary_classification",
            "params": {
                "columns_preprocessing": {},
                "target_preprocessing": [
                    "na_exclude"
                ],
                "ml_task": "binary_classification"
            }
        },
        {
            "ml_task": "binary_classification",
            "params": {
                "columns_preprocessing": {},
                "target_preprocessing": [
                    "na_exclude"
                ],
                "ml_task": "binary_classification"
            }
        }
    ],
    "learners": [
        {
            "library_version": "1.6.1",
            "algorithm_name": "Random Forest",
            "algorithm_short_name": "Random Forest",
            "uid": "d52b5b06-d4e0-4395-bc24-42ac39bdfb49",
            "params": {
                "model_type": "Random Forest",
                "ml_task": "binary_classification",
                "n_jobs": -1,
                "seed": 1235,
                "criterion": "entropy",
                "max_features": 0.5,
                "min_samples_split": 20,
                "max_depth": 4,
                "eval_metric_name": "logloss",
                "explain_level": 1
            },
            "name": "learner_fold_0"
        },
        {
            "library_version": "1.6.1",
            "algorithm_name": "Random Forest",
            "algorithm_short_name": "Random Forest",
            "uid": "bd83634a-ffa0-4ea9-a36d-72f738fc632e",
            "params": {
                "model_type": "Random Forest",
                "ml_task": "binary_classification",
                "n_jobs": -1,
                "seed": 1235,
                "criterion": "entropy",
                "max_features": 0.5,
                "min_samples_split": 20,
                "max_depth": 4,
                "eval_metric_name": "logloss",
                "explain_level": 1
            },
            "name": "learner_fold_1"
        },
        {
            "library_version": "1.6.1",
            "algorithm_name": "Random Forest",
            "algorithm_short_name": "Random Forest",
            "uid": "f57da240-7c31-4f85-998b-fabe1ffddfe0",
            "params": {
                "model_type": "Random Forest",
                "ml_task": "binary_classification",
                "n_jobs": -1,
                "seed": 1235,
                "criterion": "entropy",
                "max_features": 0.5,
                "min_samples_split": 20,
                "max_depth": 4,
                "eval_metric_name": "logloss",
                "explain_level": 1
            },
            "name": "learner_fold_2"
        },
        {
            "library_version": "1.6.1",
            "algorithm_name": "Random Forest",
            "algorithm_short_name": "Random Forest",
            "uid": "9b65e835-2f20-43b6-a4ee-5f3bafcfca07",
            "params": {
                "model_type": "Random Forest",
                "ml_task": "binary_classification",
                "n_jobs": -1,
                "seed": 1235,
                "criterion": "entropy",
                "max_features": 0.5,
                "min_samples_split": 20,
                "max_depth": 4,
                "eval_metric_name": "logloss",
                "explain_level": 1
            },
            "name": "learner_fold_3"
        },
        {
            "library_version": "1.6.1",
            "algorithm_name": "Random Forest",
            "algorithm_short_name": "Random Forest",
            "uid": "2b29c8db-3f06-46b6-86b2-b3da6e3e7d8a",
            "params": {
                "model_type": "Random Forest",
                "ml_task": "binary_classification",
                "n_jobs": -1,
                "seed": 1235,
                "criterion": "entropy",
                "max_features": 0.5,
                "min_samples_split": 20,
                "max_depth": 4,
                "eval_metric_name": "logloss",
                "explain_level": 1
            },
            "name": "learner_fold_4"
        }
    ],
    "params": {
        "additional": {
            "trees_in_step": 100,
            "train_cant_improve_limit": 1,
            "min_steps": 1,
            "max_steps": 50,
            "early_stopping_rounds": 50,
            "max_rows_limit": null,
            "max_cols_limit": null
        },
        "preprocessing": {
            "columns_preprocessing": {},
            "target_preprocessing": [
                "na_exclude"
            ],
            "ml_task": "binary_classification"
        },
        "validation_strategy": {
            "validation_type": "kfold",
            "k_folds": 5,
            "shuffle": true,
            "stratify": true,
            "X_path": "AutoML_results_perform_logloss\\X.data",
            "y_path": "AutoML_results_perform_logloss\\y.data",
            "results_path": "AutoML_results_perform_logloss"
        },
        "learner": {
            "model_type": "Random Forest",
            "ml_task": "binary_classification",
            "n_jobs": -1,
            "seed": 1235,
            "criterion": "entropy",
            "max_features": 0.5,
            "min_samples_split": 20,
            "max_depth": 4,
            "eval_metric_name": "logloss",
            "explain_level": 1
        },
        "automl_random_state": 1234,
        "ml_task": "binary_classification",
        "explain_level": 1,
        "name": "53_RandomForest",
        "status": "initialized",
        "final_loss": null,
        "train_time": null,
        "data_type": "original",
        "max_time_for_learner": 60
    },
    "saved": [
        "53_RandomForest\\learner_fold_0.random_forest",
        "53_RandomForest\\learner_fold_1.random_forest",
        "53_RandomForest\\learner_fold_2.random_forest",
        "53_RandomForest\\learner_fold_3.random_forest",
        "53_RandomForest\\learner_fold_4.random_forest"
    ],
    "predictions_fname": "53_RandomForest\\predictions_out_of_folds.csv",
    "metric_name": "logloss",
    "final_loss": "0.19835377144451938",
    "train_time": 14.061229705810547,
    "is_stacked": false,
    "joblib_version": "1.5.0",
    "threshold": 0.5241264732014363,
    "single_prediction_time": 0.13263988494873047
}