{
    "uid": "be211e05-4989-4ae6-ab38-2d3f6ca47594",
    "name": "22_LightGBM_GoldenFeatures",
    "preprocessing": [
        {
            "golden_features": {
                "new_features": [
                    {
                        "feature1": "ALLERGY ",
                        "feature2": "PEER_PRESSURE",
                        "operation": "sum",
                        "score": 0.3828137298
                    },
                    {
                        "feature1": "SWALLOWING DIFFICULTY",
                        "feature2": "ALLERGY ",
                        "operation": "sum",
                        "score": 0.4110335137
                    },
                    {
                        "feature1": "ALCOHOL CONSUMING",
                        "feature2": "PEER_PRESSURE",
                        "operation": "sum",
                        "score": 0.4421667318
                    },
                    {
                        "feature1": "WHEEZING",
                        "feature2": "ALLERGY ",
                        "operation": "sum",
                        "score": 0.4474164444
                    },
                    {
                        "feature1": "SWALLOWING DIFFICULTY",
                        "feature2": "COUGHING",
                        "operation": "sum",
                        "score": 0.4604922019
                    },
                    {
                        "feature1": "ALLERGY ",
                        "feature2": "YELLOW_FINGERS",
                        "operation": "sum",
                        "score": 0.4712114435
                    },
                    {
                        "feature1": "CHEST PAIN",
                        "feature2": "PEER_PRESSURE",
                        "operation": "sum",
                        "score": 0.4767093283
                    },
                    {
                        "feature1": "COUGHING",
                        "feature2": "ALLERGY ",
                        "operation": "sum",
                        "score": 0.4781344292
                    },
                    {
                        "feature1": "SWALLOWING DIFFICULTY",
                        "feature2": "ALCOHOL CONSUMING",
                        "operation": "sum",
                        "score": 0.4805018541
                    },
                    {
                        "feature1": "ALCOHOL CONSUMING",
                        "feature2": "ALLERGY ",
                        "operation": "sum",
                        "score": 0.4823621216
                    }
                ],
                "new_columns": [
                    "ALLERGY _sum_PEER_PRESSURE",
                    "SWALLOWING DIFFICULTY_sum_ALLERGY ",
                    "ALCOHOL CONSUMING_sum_PEER_PRESSURE",
                    "WHEEZING_sum_ALLERGY ",
                    "SWALLOWING DIFFICULTY_sum_COUGHING",
                    "ALLERGY _sum_YELLOW_FINGERS",
                    "CHEST PAIN_sum_PEER_PRESSURE",
                    "COUGHING_sum_ALLERGY ",
                    "SWALLOWING DIFFICULTY_sum_ALCOHOL CONSUMING",
                    "ALCOHOL CONSUMING_sum_ALLERGY "
                ],
                "ml_task": "binary_classification"
            },
            "ml_task": "binary_classification",
            "params": {
                "columns_preprocessing": {},
                "target_preprocessing": [
                    "na_exclude"
                ],
                "ml_task": "binary_classification",
                "golden_features": {
                    "results_path": "AutoML_results_compete_f1",
                    "ml_task": "binary_classification",
                    "n_jobs": -1
                }
            }
        },
        {
            "golden_features": {
                "new_features": [
                    {
                        "feature1": "ALLERGY ",
                        "feature2": "PEER_PRESSURE",
                        "operation": "sum",
                        "score": 0.3828137298
                    },
                    {
                        "feature1": "SWALLOWING DIFFICULTY",
                        "feature2": "ALLERGY ",
                        "operation": "sum",
                        "score": 0.4110335137
                    },
                    {
                        "feature1": "ALCOHOL CONSUMING",
                        "feature2": "PEER_PRESSURE",
                        "operation": "sum",
                        "score": 0.4421667318
                    },
                    {
                        "feature1": "WHEEZING",
                        "feature2": "ALLERGY ",
                        "operation": "sum",
                        "score": 0.4474164444
                    },
                    {
                        "feature1": "SWALLOWING DIFFICULTY",
                        "feature2": "COUGHING",
                        "operation": "sum",
                        "score": 0.4604922019
                    },
                    {
                        "feature1": "ALLERGY ",
                        "feature2": "YELLOW_FINGERS",
                        "operation": "sum",
                        "score": 0.4712114435
                    },
                    {
                        "feature1": "CHEST PAIN",
                        "feature2": "PEER_PRESSURE",
                        "operation": "sum",
                        "score": 0.4767093283
                    },
                    {
                        "feature1": "COUGHING",
                        "feature2": "ALLERGY ",
                        "operation": "sum",
                        "score": 0.4781344292
                    },
                    {
                        "feature1": "SWALLOWING DIFFICULTY",
                        "feature2": "ALCOHOL CONSUMING",
                        "operation": "sum",
                        "score": 0.4805018541
                    },
                    {
                        "feature1": "ALCOHOL CONSUMING",
                        "feature2": "ALLERGY ",
                        "operation": "sum",
                        "score": 0.4823621216
                    }
                ],
                "new_columns": [
                    "ALLERGY _sum_PEER_PRESSURE",
                    "SWALLOWING DIFFICULTY_sum_ALLERGY ",
                    "ALCOHOL CONSUMING_sum_PEER_PRESSURE",
                    "WHEEZING_sum_ALLERGY ",
                    "SWALLOWING DIFFICULTY_sum_COUGHING",
                    "ALLERGY _sum_YELLOW_FINGERS",
                    "CHEST PAIN_sum_PEER_PRESSURE",
                    "COUGHING_sum_ALLERGY ",
                    "SWALLOWING DIFFICULTY_sum_ALCOHOL CONSUMING",
                    "ALCOHOL CONSUMING_sum_ALLERGY "
                ],
                "ml_task": "binary_classification"
            },
            "ml_task": "binary_classification",
            "params": {
                "columns_preprocessing": {},
                "target_preprocessing": [
                    "na_exclude"
                ],
                "ml_task": "binary_classification",
                "golden_features": {
                    "results_path": "AutoML_results_compete_f1",
                    "ml_task": "binary_classification",
                    "n_jobs": -1
                }
            }
        },
        {
            "golden_features": {
                "new_features": [
                    {
                        "feature1": "ALLERGY ",
                        "feature2": "PEER_PRESSURE",
                        "operation": "sum",
                        "score": 0.3828137298
                    },
                    {
                        "feature1": "SWALLOWING DIFFICULTY",
                        "feature2": "ALLERGY ",
                        "operation": "sum",
                        "score": 0.4110335137
                    },
                    {
                        "feature1": "ALCOHOL CONSUMING",
                        "feature2": "PEER_PRESSURE",
                        "operation": "sum",
                        "score": 0.4421667318
                    },
                    {
                        "feature1": "WHEEZING",
                        "feature2": "ALLERGY ",
                        "operation": "sum",
                        "score": 0.4474164444
                    },
                    {
                        "feature1": "SWALLOWING DIFFICULTY",
                        "feature2": "COUGHING",
                        "operation": "sum",
                        "score": 0.4604922019
                    },
                    {
                        "feature1": "ALLERGY ",
                        "feature2": "YELLOW_FINGERS",
                        "operation": "sum",
                        "score": 0.4712114435
                    },
                    {
                        "feature1": "CHEST PAIN",
                        "feature2": "PEER_PRESSURE",
                        "operation": "sum",
                        "score": 0.4767093283
                    },
                    {
                        "feature1": "COUGHING",
                        "feature2": "ALLERGY ",
                        "operation": "sum",
                        "score": 0.4781344292
                    },
                    {
                        "feature1": "SWALLOWING DIFFICULTY",
                        "feature2": "ALCOHOL CONSUMING",
                        "operation": "sum",
                        "score": 0.4805018541
                    },
                    {
                        "feature1": "ALCOHOL CONSUMING",
                        "feature2": "ALLERGY ",
                        "operation": "sum",
                        "score": 0.4823621216
                    }
                ],
                "new_columns": [
                    "ALLERGY _sum_PEER_PRESSURE",
                    "SWALLOWING DIFFICULTY_sum_ALLERGY ",
                    "ALCOHOL CONSUMING_sum_PEER_PRESSURE",
                    "WHEEZING_sum_ALLERGY ",
                    "SWALLOWING DIFFICULTY_sum_COUGHING",
                    "ALLERGY _sum_YELLOW_FINGERS",
                    "CHEST PAIN_sum_PEER_PRESSURE",
                    "COUGHING_sum_ALLERGY ",
                    "SWALLOWING DIFFICULTY_sum_ALCOHOL CONSUMING",
                    "ALCOHOL CONSUMING_sum_ALLERGY "
                ],
                "ml_task": "binary_classification"
            },
            "ml_task": "binary_classification",
            "params": {
                "columns_preprocessing": {},
                "target_preprocessing": [
                    "na_exclude"
                ],
                "ml_task": "binary_classification",
                "golden_features": {
                    "results_path": "AutoML_results_compete_f1",
                    "ml_task": "binary_classification",
                    "n_jobs": -1
                }
            }
        },
        {
            "golden_features": {
                "new_features": [
                    {
                        "feature1": "ALLERGY ",
                        "feature2": "PEER_PRESSURE",
                        "operation": "sum",
                        "score": 0.3828137298
                    },
                    {
                        "feature1": "SWALLOWING DIFFICULTY",
                        "feature2": "ALLERGY ",
                        "operation": "sum",
                        "score": 0.4110335137
                    },
                    {
                        "feature1": "ALCOHOL CONSUMING",
                        "feature2": "PEER_PRESSURE",
                        "operation": "sum",
                        "score": 0.4421667318
                    },
                    {
                        "feature1": "WHEEZING",
                        "feature2": "ALLERGY ",
                        "operation": "sum",
                        "score": 0.4474164444
                    },
                    {
                        "feature1": "SWALLOWING DIFFICULTY",
                        "feature2": "COUGHING",
                        "operation": "sum",
                        "score": 0.4604922019
                    },
                    {
                        "feature1": "ALLERGY ",
                        "feature2": "YELLOW_FINGERS",
                        "operation": "sum",
                        "score": 0.4712114435
                    },
                    {
                        "feature1": "CHEST PAIN",
                        "feature2": "PEER_PRESSURE",
                        "operation": "sum",
                        "score": 0.4767093283
                    },
                    {
                        "feature1": "COUGHING",
                        "feature2": "ALLERGY ",
                        "operation": "sum",
                        "score": 0.4781344292
                    },
                    {
                        "feature1": "SWALLOWING DIFFICULTY",
                        "feature2": "ALCOHOL CONSUMING",
                        "operation": "sum",
                        "score": 0.4805018541
                    },
                    {
                        "feature1": "ALCOHOL CONSUMING",
                        "feature2": "ALLERGY ",
                        "operation": "sum",
                        "score": 0.4823621216
                    }
                ],
                "new_columns": [
                    "ALLERGY _sum_PEER_PRESSURE",
                    "SWALLOWING DIFFICULTY_sum_ALLERGY ",
                    "ALCOHOL CONSUMING_sum_PEER_PRESSURE",
                    "WHEEZING_sum_ALLERGY ",
                    "SWALLOWING DIFFICULTY_sum_COUGHING",
                    "ALLERGY _sum_YELLOW_FINGERS",
                    "CHEST PAIN_sum_PEER_PRESSURE",
                    "COUGHING_sum_ALLERGY ",
                    "SWALLOWING DIFFICULTY_sum_ALCOHOL CONSUMING",
                    "ALCOHOL CONSUMING_sum_ALLERGY "
                ],
                "ml_task": "binary_classification"
            },
            "ml_task": "binary_classification",
            "params": {
                "columns_preprocessing": {},
                "target_preprocessing": [
                    "na_exclude"
                ],
                "ml_task": "binary_classification",
                "golden_features": {
                    "results_path": "AutoML_results_compete_f1",
                    "ml_task": "binary_classification",
                    "n_jobs": -1
                }
            }
        },
        {
            "golden_features": {
                "new_features": [
                    {
                        "feature1": "ALLERGY ",
                        "feature2": "PEER_PRESSURE",
                        "operation": "sum",
                        "score": 0.3828137298
                    },
                    {
                        "feature1": "SWALLOWING DIFFICULTY",
                        "feature2": "ALLERGY ",
                        "operation": "sum",
                        "score": 0.4110335137
                    },
                    {
                        "feature1": "ALCOHOL CONSUMING",
                        "feature2": "PEER_PRESSURE",
                        "operation": "sum",
                        "score": 0.4421667318
                    },
                    {
                        "feature1": "WHEEZING",
                        "feature2": "ALLERGY ",
                        "operation": "sum",
                        "score": 0.4474164444
                    },
                    {
                        "feature1": "SWALLOWING DIFFICULTY",
                        "feature2": "COUGHING",
                        "operation": "sum",
                        "score": 0.4604922019
                    },
                    {
                        "feature1": "ALLERGY ",
                        "feature2": "YELLOW_FINGERS",
                        "operation": "sum",
                        "score": 0.4712114435
                    },
                    {
                        "feature1": "CHEST PAIN",
                        "feature2": "PEER_PRESSURE",
                        "operation": "sum",
                        "score": 0.4767093283
                    },
                    {
                        "feature1": "COUGHING",
                        "feature2": "ALLERGY ",
                        "operation": "sum",
                        "score": 0.4781344292
                    },
                    {
                        "feature1": "SWALLOWING DIFFICULTY",
                        "feature2": "ALCOHOL CONSUMING",
                        "operation": "sum",
                        "score": 0.4805018541
                    },
                    {
                        "feature1": "ALCOHOL CONSUMING",
                        "feature2": "ALLERGY ",
                        "operation": "sum",
                        "score": 0.4823621216
                    }
                ],
                "new_columns": [
                    "ALLERGY _sum_PEER_PRESSURE",
                    "SWALLOWING DIFFICULTY_sum_ALLERGY ",
                    "ALCOHOL CONSUMING_sum_PEER_PRESSURE",
                    "WHEEZING_sum_ALLERGY ",
                    "SWALLOWING DIFFICULTY_sum_COUGHING",
                    "ALLERGY _sum_YELLOW_FINGERS",
                    "CHEST PAIN_sum_PEER_PRESSURE",
                    "COUGHING_sum_ALLERGY ",
                    "SWALLOWING DIFFICULTY_sum_ALCOHOL CONSUMING",
                    "ALCOHOL CONSUMING_sum_ALLERGY "
                ],
                "ml_task": "binary_classification"
            },
            "ml_task": "binary_classification",
            "params": {
                "columns_preprocessing": {},
                "target_preprocessing": [
                    "na_exclude"
                ],
                "ml_task": "binary_classification",
                "golden_features": {
                    "results_path": "AutoML_results_compete_f1",
                    "ml_task": "binary_classification",
                    "n_jobs": -1
                }
            }
        }
    ],
    "learners": [
        {
            "library_version": "4.6.0",
            "algorithm_name": "LightGBM",
            "algorithm_short_name": "LightGBM",
            "uid": "73d59a20-e1c4-4902-a035-ec2678d6e6f4",
            "params": {
                "model_type": "LightGBM",
                "ml_task": "binary_classification",
                "n_jobs": -1,
                "seed": 1236,
                "objective": "binary",
                "num_leaves": 63,
                "learning_rate": 0.2,
                "feature_fraction": 0.5,
                "bagging_fraction": 1.0,
                "min_data_in_leaf": 10,
                "metric": "custom",
                "custom_eval_metric_name": "f1",
                "explain_level": 0
            },
            "name": "learner_fold_0"
        },
        {
            "library_version": "4.6.0",
            "algorithm_name": "LightGBM",
            "algorithm_short_name": "LightGBM",
            "uid": "d9a8e8b6-979e-446a-8a8c-52e1ad8b3d80",
            "params": {
                "model_type": "LightGBM",
                "ml_task": "binary_classification",
                "n_jobs": -1,
                "seed": 1236,
                "objective": "binary",
                "num_leaves": 63,
                "learning_rate": 0.2,
                "feature_fraction": 0.5,
                "bagging_fraction": 1.0,
                "min_data_in_leaf": 10,
                "metric": "custom",
                "custom_eval_metric_name": "f1",
                "explain_level": 0
            },
            "name": "learner_fold_1"
        },
        {
            "library_version": "4.6.0",
            "algorithm_name": "LightGBM",
            "algorithm_short_name": "LightGBM",
            "uid": "28ba9851-eddf-4217-852a-dd1555e1e48d",
            "params": {
                "model_type": "LightGBM",
                "ml_task": "binary_classification",
                "n_jobs": -1,
                "seed": 1236,
                "objective": "binary",
                "num_leaves": 63,
                "learning_rate": 0.2,
                "feature_fraction": 0.5,
                "bagging_fraction": 1.0,
                "min_data_in_leaf": 10,
                "metric": "custom",
                "custom_eval_metric_name": "f1",
                "explain_level": 0
            },
            "name": "learner_fold_2"
        },
        {
            "library_version": "4.6.0",
            "algorithm_name": "LightGBM",
            "algorithm_short_name": "LightGBM",
            "uid": "224c17e8-996b-45b2-8975-99e2cb6474ac",
            "params": {
                "model_type": "LightGBM",
                "ml_task": "binary_classification",
                "n_jobs": -1,
                "seed": 1236,
                "objective": "binary",
                "num_leaves": 63,
                "learning_rate": 0.2,
                "feature_fraction": 0.5,
                "bagging_fraction": 1.0,
                "min_data_in_leaf": 10,
                "metric": "custom",
                "custom_eval_metric_name": "f1",
                "explain_level": 0
            },
            "name": "learner_fold_3"
        },
        {
            "library_version": "4.6.0",
            "algorithm_name": "LightGBM",
            "algorithm_short_name": "LightGBM",
            "uid": "df2e9494-760b-4485-bfd0-b505a62931b9",
            "params": {
                "model_type": "LightGBM",
                "ml_task": "binary_classification",
                "n_jobs": -1,
                "seed": 1236,
                "objective": "binary",
                "num_leaves": 63,
                "learning_rate": 0.2,
                "feature_fraction": 0.5,
                "bagging_fraction": 1.0,
                "min_data_in_leaf": 10,
                "metric": "custom",
                "custom_eval_metric_name": "f1",
                "explain_level": 0
            },
            "name": "learner_fold_4"
        }
    ],
    "params": {
        "additional": {
            "max_rounds": 10000,
            "early_stopping_rounds": 50,
            "max_rows_limit": null,
            "max_cols_limit": null
        },
        "preprocessing": {
            "columns_preprocessing": {},
            "target_preprocessing": [
                "na_exclude"
            ],
            "ml_task": "binary_classification",
            "golden_features": {
                "results_path": "AutoML_results_compete_f1",
                "ml_task": "binary_classification",
                "n_jobs": -1
            }
        },
        "validation_strategy": {
            "validation_type": "kfold",
            "shuffle": true,
            "stratify": true,
            "X_path": "AutoML_results_compete_f1\\X.data",
            "y_path": "AutoML_results_compete_f1\\y.data",
            "results_path": "AutoML_results_compete_f1",
            "k_folds": 5
        },
        "learner": {
            "model_type": "LightGBM",
            "ml_task": "binary_classification",
            "n_jobs": -1,
            "seed": 1236,
            "objective": "binary",
            "num_leaves": 63,
            "learning_rate": 0.2,
            "feature_fraction": 0.5,
            "bagging_fraction": 1.0,
            "min_data_in_leaf": 10,
            "metric": "custom",
            "custom_eval_metric_name": "f1",
            "explain_level": 0
        },
        "automl_random_state": 1234,
        "ml_task": "binary_classification",
        "explain_level": 0,
        "name": "22_LightGBM_GoldenFeatures",
        "status": "initialized",
        "final_loss": null,
        "train_time": null,
        "data_type": "original_golden_features",
        "max_time_for_learner": 60
    },
    "saved": [
        "22_LightGBM_GoldenFeatures\\learner_fold_0.lightgbm",
        "22_LightGBM_GoldenFeatures\\learner_fold_1.lightgbm",
        "22_LightGBM_GoldenFeatures\\learner_fold_2.lightgbm",
        "22_LightGBM_GoldenFeatures\\learner_fold_3.lightgbm",
        "22_LightGBM_GoldenFeatures\\learner_fold_4.lightgbm"
    ],
    "predictions_fname": "22_LightGBM_GoldenFeatures\\predictions_out_of_folds.csv",
    "metric_name": "f1",
    "final_loss": "-0.9623059866962306",
    "train_time": 12.962774515151978,
    "is_stacked": false,
    "joblib_version": "1.5.0",
    "threshold": 0.5092476508631463
}